cleverwrap/__init__.py
cleverwrap/cleverwrap.py
cleverwrap/conversation.py
cleverwrap/errors.py
cleverwrap/response.py
cleverwrap-0.3.0.2.dist-info/LICENSE.txt
cleverwrap-0.3.0.2.dist-info/METADATA
cleverwrap-0.3.0.2.dist-info/WHEEL
cleverwrap-0.3.0.2.dist-info/top_level.txt
cleverwrap-0.3.0.2.dist-info/RECORD
