Metadata-Version: 2.1
Name: cleverwrap
Version: 0.3.0.2
Summary: A wrapper for the official cleverbot.com API
Home-page: https://github.com/snoonetIRC/cleverwrap.py
Author: Andrew Edwards
Author-email: andrewthomasedwards@gmail.com
License: MIT
Keywords: cleverbot,wrapper,clever
Platform: UNKNOWN
Classifier: Programming Language :: Python :: 3 :: Only
Classifier: License :: OSI Approved :: MIT License
Classifier: Intended Audience :: Developers
Classifier: Natural Language :: English
